{
  "skills": [
    {
      "id": "genesis:speedster/speed_1",
      "name": "Speed Boost",
      "description": "Grants an increased speed cap.",
      "cost": 1,
      "prerequisites": [],
      "x": 10,
      "y": 50,
      "type": "PASSIVE"
    },
    {
      "id": "genesis:speedster/speed_2",
      "name": "Speed Boost",
      "description": "Grants an increased speed cap.",
      "cost": 2,
      "prerequisites": [
        "genesis:speedster/speed_1"
      ],
      "x": 50,
      "y": 90,
      "type": "PASSIVE"
    },
    {
      "id": "genesis:speedster/speed_3",
      "name": "Speed Boost",
      "description": "Grants an increased speed cap.",
      "cost": 3,
      "prerequisites": [
        "genesis:speedster/speed_2"
      ],
      "x": 90,
      "y": 50,
      "type": "PASSIVE"
    },
    {
      "id": "genesis:speedster/speed_4",
      "name": "Speed Boost",
      "description": "Grants an increased speed cap.",
      "cost": 3,
      "prerequisites": [
        "genesis:speedster/speed_3"
      ],
      "x": 130,
      "y": 90,
      "type": "PASSIVE"
    },
    {
      "id": "genesis:speedster/speed_5",
      "name": "Speed Boost",
      "description": "Grants an increased speed cap.",
      "cost": 3,
      "prerequisites": [
        "genesis:speedster/speed_4"
      ],
      "x": 170,
      "y": 50,
      "type": "PASSIVE"
    },
    {
      "id": "genesis:speedster/speed_6",
      "name": "Speed Boost",
      "description": "Grants an increased speed cap.",
      "cost": 3,
      "prerequisites": [
        "genesis:speedster/speed_5"
      ],
      "x": 210,
      "y": 90,
      "type": "PASSIVE"
    },
    {
      "id": "genesis:speedster/speed_7",
      "name": "Speed Boost",
      "description": "Grants an increased speed cap.",
      "cost": 3,
      "prerequisites": [
        "genesis:speedster/speed_6"
      ],
      "x": 250,
      "y": 50,
      "type": "PASSIVE"
    },
    {
      "id": "genesis:speedster/speed_8",
      "name": "Speed Boost",
      "description": "Grants an increased speed cap.",
      "cost": 3,
      "prerequisites": [
        "genesis:speedster/speed_7"
      ],
      "x": 290,
      "y": 90,
      "type": "PASSIVE"
    },
    {
      "id": "genesis:speedster/kinetic_kickstart",
      "name": "Kinetic Kickstart",
      "description": "Reach your top speed instantly.",
      "cost": 5,
      "prerequisites": [
        "genesis:speedster/speed_8"
      ],
      "x": 290,
      "y": 50,
      "type": "PASSIVE"
    }
  ]
}
